{
  "verdict": "TIGHTENED",
  "sources": [
    "ai3_wave"
  ],
  "rules": {
    "action": "Reduce position size. Tight stops. Wait for conditions to clear."
  },
  "modules": {
    "black_swan": {
      "state": "PROCEED",
      "score": 0
    },
    "vix_spx": {
      "state": "PROCEED",
      "vix": null,
      "spx_change": -0.75,
      "vix_weekly_chg": 5.7
    },
    "ai3_wave": {
      "state": "TIGHTENED",
      "active": true
    },
    "stablecoins": {
      "state": "PROCEED"
    },
    "session": {
      "state": "PROCEED",
      "name": "Unknown",
      "ny_open": "13:30 UTC",
      "golden_window": null,
      "is_weekend": false
    }
  },
  "timestamp": "2026-06-23 14:15 UTC",
  "_collected": "2026-06-23 14:15 UTC"
}
